RequireVPN/Exceptions.py
RequireVPN/RequireVPN.py
RequireVPN/__init__.py
RequireVPN-0.0.2.dist-info/LICENSE
RequireVPN-0.0.2.dist-info/METADATA
RequireVPN-0.0.2.dist-info/WHEEL
RequireVPN-0.0.2.dist-info/top_level.txt
RequireVPN-0.0.2.dist-info/RECORD
