Metadata-Version: 2.1
Name: RequireVPN
Version: 0.0.2
Summary: Python Library To Require VPN Connections
Home-page: https://github.com/xFueY/RequireVPN/
Author: xFueY
Author-email: xFueY@protonmail.com
License: MIT
Keywords: RequireVPN
Platform: UNKNOWN
Classifier: Development Status :: 5 - Production/Stable
Classifier: Intended Audience :: Developers
Classifier: License :: OSI Approved :: MIT License
Classifier: Natural Language :: English
Classifier: Programming Language :: Python :: 3.8
Requires-Dist: requests
